morgan_linter/__init__.py
morgan_linter/__main__.py
morgan_linter/base_linter.py
morgan_linter/custom_linter.py
morgan_linter/google_checks.py
morgan_linter/utils.py
morgan_linter-1.2.1.dist-info/entry_points.txt
morgan_linter-1.2.1.dist-info/WHEEL
morgan_linter-1.2.1.dist-info/LICENSE
morgan_linter-1.2.1.dist-info/METADATA
morgan_linter-1.2.1.dist-info/RECORD
