Metadata-Version: 2.1
Name: morgan-linter
Version: 1.2.1
Summary: Linter to validate google docstrings
Author: Edwar Girón
Author-email: contactoedwargiron@gmail.com
Requires-Python: >=3.8
Classifier: Programming Language :: Python :: 3
Classifier: Programming Language :: Python :: 3.8
Classifier: Programming Language :: Python :: 3.9
Classifier: Programming Language :: Python :: 3.10
Classifier: Programming Language :: Python :: 3.11
